minimal_user/__init__.py
minimal_user/admin.py
minimal_user/managers.py
minimal_user/models.py
minimal_user/drf/__init__.py
minimal_user/drf/serializers.py
minimal_user/migrations/0001_initial.py
minimal_user/migrations/__init__.py
django_minimal_user-0.9.2.dist-info/LICENSE
django_minimal_user-0.9.2.dist-info/METADATA
django_minimal_user-0.9.2.dist-info/WHEEL
django_minimal_user-0.9.2.dist-info/top_level.txt
django_minimal_user-0.9.2.dist-info/RECORD
